docs/CODE_OF_CONDUCT.md
docs/CONFIG.md
docs/DRIVERS.md
docs/INSTALL.md
docs/LOADING_SUPPORT.md
docs/MAINT.md
docs/Makefile
docs/RECORDS_SPEC.md
docs/SECURITY.md
docs/records-mover-horizontal.png
docs/terminalizer.yml
docs/schema/Makefile
docs/schema/SCHEMAv1.md
docs/schema/pandas_example_1.json
docs/schema/records_schema_v1_schema.json
docs/schema/redshift_example_1.json
docs/source/conf.py
docs/source/index.rst
docs/source/records_mover.airflow.hooks.rst
docs/source/records_mover.airflow.rst
docs/source/records_mover.records.rst
docs/source/records_mover.records.sources.rst
docs/source/records_mover.records.targets.rst
docs/source/records_mover.rst
docs/source/_static/.gitkeep
metrics/brakeman_high_water_mark
metrics/bundle-audit_high_water_mark
metrics/cane_high_water_mark
metrics/coverage_high_water_mark
metrics/flake8_high_water_mark
metrics/flay_high_water_mark
metrics/flog_high_water_mark
metrics/mdl_high_water_mark
metrics/mypy_high_water_mark
metrics/punchlist_high_water_mark
metrics/pycodestyle_high_water_mark
metrics/rails_best_practices_high_water_mark
metrics/reek_high_water_mark
metrics/rubocop_high_water_mark
metrics/scalastyle_high_water_mark
metrics/shellcheck_high_water_mark
records_mover/__init__.py
records_mover/check_db_conn_engine.py
records_mover/logging.py
records_mover/mover_types.py
records_mover/py.typed
records_mover/session.py
records_mover/version.py
records_mover/airflow/__init__.py
records_mover/airflow/hooks/__init__.py
records_mover/airflow/hooks/google_cloud_credentials_hook.py
records_mover/airflow/hooks/records_hook.py
records_mover/airflow/hooks/sqlalchemy_db_hook.py
records_mover/cli/__init__.py
records_mover/cli/job_config_schema_as_args_parser.py
records_mover/creds/__init__.py
records_mover/creds/base_creds.py
records_mover/creds/creds_via_airflow.py
records_mover/creds/creds_via_env.py
records_mover/creds/creds_via_lastpass.py
records_mover/creds/database.py
records_mover/db/__init__.py
records_mover/db/connect.py
records_mover-1.6.4.dist-info/LICENSE
records_mover-1.6.4.dist-info/METADATA
records_mover-1.6.4.dist-info/WHEEL
records_mover-1.6.4.dist-info/entry_points.txt
records_mover-1.6.4.dist-info/top_level.txt
records_mover-1.6.4.dist-info/RECORD
