Metadata-Version: 2.1
Name: records-mover
Version: 1.6.4
Summary: Records mover is a command-line tool and Python library you can use to move relational data from one place to another.
License: Apache License
Project-URL: Repository, https://github.com/bluelabsio/records-mover
Classifier: Development Status :: 4 - Beta
Classifier: Intended Audience :: Developers
Classifier: Topic :: Database :: Front-Ends
Classifier: License :: OSI Approved :: Apache Software License
Classifier: Programming Language :: Python :: 3
Classifier: Programming Language :: Python :: 3.6
Classifier: Programming Language :: Python :: 3.7
Classifier: Programming Language :: Python :: 3.8
Classifier: Programming Language :: Python :: 3.9
Requires-Python: >=3.8
License-File: LICENSE
Requires-Dist: timeout-decorator
Requires-Dist: PyYAML >=3.10
Requires-Dist: db-facts >=5
Requires-Dist: chardet >=3
Requires-Dist: tenacity >=8.0.1
Requires-Dist: config-resolver <6,>=5.0.1
Requires-Dist: typing-inspect
Requires-Dist: typing-extensions
Provides-Extra: airflow
Requires-Dist: apache-airflow >=2 ; extra == 'airflow'
Requires-Dist: apache-airflow-providers-amazon ; extra == 'airflow'
Requires-Dist: apache-airflow-providers-google ; extra == 'airflow'
Provides-Extra: alldb
Requires-Dist: records-mover[bigquery,mysql,postgres-binary,redshift-binary,vertica] ; extra == 'alldb'
Provides-Extra: aws
Requires-Dist: awscli >=1.32.14 ; extra == 'aws'
Requires-Dist: boto3 ; extra == 'aws'
Requires-Dist: s3-concat >=0.1.7 ; extra == 'aws'
Requires-Dist: records-mover[smart-open] ; extra == 'aws'
Provides-Extra: bigquery
Requires-Dist: sqlalchemy-bigquery ; extra == 'bigquery'
Requires-Dist: records-mover[db,gcs] ; extra == 'bigquery'
Provides-Extra: cli
Requires-Dist: odictliteral ; extra == 'cli'
Requires-Dist: jsonschema ; extra == 'cli'
Requires-Dist: docstring-parser ; extra == 'cli'
Requires-Dist: requests ; extra == 'cli'
Provides-Extra: db
Requires-Dist: sqlalchemy <2,>=1.4 ; extra == 'db'
Requires-Dist: sqlalchemy-privileges >=0.2.0 ; extra == 'db'
Provides-Extra: docs
Requires-Dist: sphinx >=5 ; extra == 'docs'
Requires-Dist: sphinx-rtd-theme >=1 ; extra == 'docs'
Requires-Dist: sphinx-argparse ; extra == 'docs'
Requires-Dist: readthedocs-sphinx-ext >=2 ; extra == 'docs'
Requires-Dist: recommonmark ; extra == 'docs'
Requires-Dist: records-mover[airflow,aws,cli,db] ; extra == 'docs'
Provides-Extra: gcs
Requires-Dist: google-cloud-storage ; extra == 'gcs'
Requires-Dist: records-mover[smart-open] ; extra == 'gcs'
Provides-Extra: google-api-client
Requires-Dist: google-api-python-client >=1.8.0 ; extra == 'google-api-client'
Requires-Dist: grpcio <2.0dev,>=1.29.0 ; extra == 'google-api-client'
Provides-Extra: gsheets
Requires-Dist: google ; extra == 'gsheets'
Requires-Dist: google-auth-httplib2 ; extra == 'gsheets'
Requires-Dist: PyOpenSSL ; extra == 'gsheets'
Requires-Dist: records-mover[google-api-client] ; extra == 'gsheets'
Provides-Extra: itest
Requires-Dist: jsonschema ; extra == 'itest'
Requires-Dist: pytz ; extra == 'itest'
Requires-Dist: wheel ; extra == 'itest'
Requires-Dist: parameterized ; extra == 'itest'
Requires-Dist: records-mover[google-api-client,pytest] ; extra == 'itest'
Provides-Extra: mysql
Requires-Dist: pymysql ; extra == 'mysql'
Requires-Dist: records-mover[db] ; extra == 'mysql'
Provides-Extra: pandas
Requires-Dist: pandas <2,>=1.3.5 ; extra == 'pandas'
Provides-Extra: parquet
Requires-Dist: pyarrow ; extra == 'parquet'
Provides-Extra: postgres-base
Requires-Dist: records-mover[db] ; extra == 'postgres-base'
Provides-Extra: postgres-binary
Requires-Dist: psycopg2-binary ; extra == 'postgres-binary'
Requires-Dist: records-mover[postgres-base] ; extra == 'postgres-binary'
Provides-Extra: postgres-source
Requires-Dist: psycopg2 ; extra == 'postgres-source'
Requires-Dist: records-mover[postgres-base] ; extra == 'postgres-source'
Provides-Extra: pytest
Requires-Dist: pytest <8.2 ; extra == 'pytest'
Requires-Dist: pytest-cov ; extra == 'pytest'
Provides-Extra: redshift-base
Requires-Dist: sqlalchemy-redshift >=0.7.7 ; extra == 'redshift-base'
Requires-Dist: records-mover[aws,db] ; extra == 'redshift-base'
Provides-Extra: redshift-binary
Requires-Dist: psycopg2-binary ; extra == 'redshift-binary'
Requires-Dist: records-mover[redshift-base] ; extra == 'redshift-binary'
Provides-Extra: redshift-source
Requires-Dist: psycopg2 ; extra == 'redshift-source'
Requires-Dist: records-mover[redshift-base] ; extra == 'redshift-source'
Provides-Extra: smart-open
Requires-Dist: smart-open >=2 ; extra == 'smart-open'
Provides-Extra: typecheck
Requires-Dist: mypy >=1.7.1 ; extra == 'typecheck'
Requires-Dist: lxml ; extra == 'typecheck'
Requires-Dist: sqlalchemy-stubs >=0.3 ; extra == 'typecheck'
Requires-Dist: types-pytz ; extra == 'typecheck'
Requires-Dist: types-mock ; extra == 'typecheck'
Provides-Extra: unittest
Requires-Dist: coverage ; extra == 'unittest'
Requires-Dist: mock ; extra == 'unittest'
Requires-Dist: records-mover[airflow,alldb,aws,cli,gcs,gsheets,pandas,pytest] ; extra == 'unittest'
Provides-Extra: vertica
Requires-Dist: sqlalchemy-vertica-python >=0.5.5 ; extra == 'vertica'
Requires-Dist: records-mover[db] ; extra == 'vertica'
